{
  "aircraft": {
    "aircraftModel": "Embraer 191",
    "aircraftTotalCapacity": 100,
    "aircraftEconomySeats": 68,
    "aircraftPremiumSeats": 16,
    "aircraftBusinessSeats": 16,
    "aircraftFirstClassSeats": 0
  },
  "seatClasses": [
    {
      "seatClassName": "BUSINESS",
      "basePrice": 200.0
    },
    {
      "seatClassName": "PREMIUM",
      "basePrice": 150.0
    },
    {
      "seatClassName": "ECONOMY",
      "basePrice": 100.0
    }
  ],
  "seats": [
    {
      "seatNumber": "1A",
      "rowNumber": 1,
      "seatLetter": "A",
      "seatClassName": "BUSINESS",
      "window": true,
      "aisle": false,
      "extraLegroom": true,
      "exitRow": true
    },
    {
      "seatNumber": "1C",
      "rowNumber": 1,
      "seatLetter": "C",
      "seatClassName": "BUSINESS",
      "window": false,
      "aisle": true,
      "extraLegroom": true,
      "exitRow": true
    },
    {
      "seatNumber": "1D",
      "rowNumber": 1,
      "seatLetter": "D",
      "seatClassName": "BUSINESS",
      "window": false,
      "aisle": true,
      "extraLegroom": true,
      "exitRow": true
    },
    {
      "seatNumber": "1F",
      "rowNumber": 1,
      "seatLetter": "F",
      "seatClassName": "BUSINESS",
      "window": true,
      "aisle": false,
      "extraLegroom": true,
      "exitRow": true
    },
    {
      "seatNumber": "2A",
      "rowNumber": 2,
      "seatLetter": "A",
      "seatClassName": "BUSINESS",
      "window":true,
      "aisle": false,
      "extraLegroom": false,
      "exitRow": true
    },
    {
      "seatNumber": "2C",
      "rowNumber": 2,
      "seatLetter": "C",
      "seatClassName": "BUSINESS",
      "window": false,
      "aisle": true,
      "extraLegroom": false,
      "exitRow": true
    },
    {
      "seatNumber": "2D",
      "rowNumber": 2,
      "seatLetter": "D",
      "seatClassName": "BUSINESS",
      "window": false,
      "aisle": true,
      "extraLegroom": false,
      "exitRow": true
    },
    {
      "seatNumber": "2F",
      "rowNumber": 2,
      "seatLetter": "F",
      "seatClassName": "BUSINESS",
      "window": true,
      "aisle": false,
      "extraLegroom": false,
      "exitRow": true
    },
    {
      "seatNumber": "3A",
      "rowNumber": 3,
      "seatLetter": "A",
      "seatClassName": "BUSINESS",
      "window":true,
      "aisle": false,
      "extraLegroom": false,
      "exitRow": false
    },
    {
      "seatNumber": "3C",
      "rowNumber": 3,
      "seatLetter": "C",
      "seatClassName": "BUSINESS",
      "window": false,
      "aisle": true,
      "extraLegroom": false,
      "exitRow": false
    },
    {
      "seatNumber": "3D",
      "rowNumber": 3,
      "seatLetter": "D",
      "seatClassName": "BUSINESS",
      "window": false,
      "aisle": true,
      "extraLegroom": false,
      "exitRow": false
    },
    {
      "seatNumber": "3F",
      "rowNumber": 3,
      "seatLetter": "F",
      "seatClassName": "BUSINESS",
      "window": true,
      "aisle": false,
      "extraLegroom": false,
      "exitRow": false
    },
    {
      "seatNumber": "4A",
      "rowNumber": 4,
      "seatLetter": "A",
      "seatClassName": "BUSINESS",
      "window":true,
      "aisle": false,
      "extraLegroom": false,
      "exitRow": false
    },
    {
      "seatNumber": "4C",
      "rowNumber": 4,
      "seatLetter": "C",
      "seatClassName": "BUSINESS",
      "window": false,
      "aisle": true,
      "extraLegroom": false,
      "exitRow": false
    },
    {
      "seatNumber": "4D",
      "rowNumber": 4,
      "seatLetter": "D",
      "seatClassName": "BUSINESS",
      "window": false,
      "aisle": true,
      "extraLegroom": false,
      "exitRow": false
    },
    {
      "seatNumber": "4F",
      "rowNumber": 4,
      "seatLetter": "F",
      "seatClassName": "BUSINESS",
      "window": true,
      "aisle": false,
      "extraLegroom": false,
      "exitRow": false
    },
    {
      "seatNumber": "5A",
      "rowNumber": 5,
      "seatLetter": "A",
      "seatClassName": "PREMIUM",
      "window":true,
      "aisle": false,
      "extraLegroom": false,
      "exitRow": false
    },
    {
      "seatNumber": "5C",
      "rowNumber": 5,
      "seatLetter": "C",
      "seatClassName": "PREMIUM",
      "window": false,
      "aisle": true,
      "extraLegroom": false,
      "exitRow": false
    },
    {
      "seatNumber": "5D",
      "rowNumber": 5,
      "seatLetter": "D",
      "seatClassName": "PREMIUM",
      "window": false,
      "aisle": true,
      "extraLegroom": false,
      "exitRow": false
    },
    {
      "seatNumber": "5F",
      "rowNumber": 5,
      "seatLetter": "F",
      "seatClassName": "PREMIUM",
      "window": true,
      "aisle": false,
      "extraLegroom": false,
      "exitRow": false
    },
    {
      "seatNumber": "6A",
      "rowNumber": 6,
      "seatLetter": "A",
      "seatClassName": "PREMIUM",
      "window":true,
      "aisle": false,
      "extraLegroom": false,
      "exitRow": false
    },
    {
      "seatNumber": "6C",
      "rowNumber": 6,
      "seatLetter": "C",
      "seatClassName": "PREMIUM",
      "window": false,
      "aisle": true,
      "extraLegroom": false,
      "exitRow": false
    },
    {
      "seatNumber": "6D",
      "rowNumber": 6,
      "seatLetter": "D",
      "seatClassName": "PREMIUM",
      "window": false,
      "aisle": true,
      "extraLegroom": false,
      "exitRow": false
    },
    {
      "seatNumber": "6F",
      "rowNumber": 6,
      "seatLetter": "F",
      "seatClassName": "PREMIUM",
      "window": true,
      "aisle": false,
      "extraLegroom": false,
      "exitRow": false
    },
    {
      "seatNumber": "7A",
      "rowNumber": 7,
      "seatLetter": "A",
      "seatClassName": "PREMIUM",
      "window":true,
      "aisle": false,
      "extraLegroom": false,
      "exitRow": false
    },
    {
      "seatNumber": "7C",
      "rowNumber": 7,
      "seatLetter": "C",
      "seatClassName": "PREMIUM",
      "window": false,
      "aisle": true,
      "extraLegroom": false,
      "exitRow": false
    },
    {
      "seatNumber": "7D",
      "rowNumber": 7,
      "seatLetter": "D",
      "seatClassName": "PREMIUM",
      "window": false,
      "aisle": true,
      "extraLegroom": false,
      "exitRow": false
    },
    {
      "seatNumber": "7F",
      "rowNumber": 7,
      "seatLetter": "F",
      "seatClassName": "PREMIUM",
      "window": true,
      "aisle": false,
      "extraLegroom": false,
      "exitRow": false
    },
    {
      "seatNumber": "8A",
      "rowNumber": 8,
      "seatLetter": "A",
      "seatClassName": "PREMIUM",
      "window":true,
      "aisle": false,
      "extraLegroom": false,
      "exitRow": false
    },
    {
      "seatNumber": "8C",
      "rowNumber": 8,
      "seatLetter": "C",
      "seatClassName": "PREMIUM",
      "window": false,
      "aisle": true,
      "extraLegroom": false,
      "exitRow": false
    },
    {
      "seatNumber": "8D",
      "rowNumber": 8,
      "seatLetter": "D",
      "seatClassName": "PREMIUM",
      "window": false,
      "aisle": true,
      "extraLegroom": false,
      "exitRow": false
    },
    {
      "seatNumber": "8F",
      "rowNumber": 8,
      "seatLetter": "F",
      "seatClassName": "PREMIUM",
      "window": true,
      "aisle": false,
      "extraLegroom": false,
      "exitRow": false
    },
    {
      "seatNumber": "9A",
      "rowNumber": 9,
      "seatLetter": "A",
      "seatClassName": "ECONOMY",
      "window":true,
      "aisle": false,
      "extraLegroom": false,
      "exitRow": true
    },
    {
      "seatNumber": "9C",
      "rowNumber": 9,
      "seatLetter": "C",
      "seatClassName": "ECONOMY",
      "window": false,
      "aisle": true,
      "extraLegroom": false,
      "exitRow": true
    },
    {
      "seatNumber": "9D",
      "rowNumber": 9,
      "seatLetter": "D",
      "seatClassName": "ECONOMY",
      "window": false,
      "aisle": true,
      "extraLegroom": false,
      "exitRow": true
    },
    {
      "seatNumber": "9F",
      "rowNumber": 9,
      "seatLetter": "F",
      "seatClassName": "ECONOMY",
      "window": true,
      "aisle": false,
      "extraLegroom": false,
      "exitRow": true
    },
    {
      "seatNumber": "10A",
      "rowNumber": 10,
      "seatLetter": "A",
      "seatClassName": "ECONOMY",
      "window":true,
      "aisle": false,
      "extraLegroom": false,
      "exitRow": true
    },
    {
      "seatNumber": "10C",
      "rowNumber": 10,
      "seatLetter": "C",
      "seatClassName": "ECONOMY",
      "window": false,
      "aisle": true,
      "extraLegroom": false,
      "exitRow": true
    },
    {
      "seatNumber": "10D",
      "rowNumber": 10,
      "seatLetter": "D",
      "seatClassName": "ECONOMY",
      "window": false,
      "aisle": true,
      "extraLegroom": false,
      "exitRow": true
    },
    {
      "seatNumber": "10F",
      "rowNumber": 10,
      "seatLetter": "F",
      "seatClassName": "ECONOMY",
      "window": true,
      "aisle": false,
      "extraLegroom": false,
      "exitRow": true
    },
    {
      "seatNumber": "11A",
      "rowNumber": 11,
      "seatLetter": "A",
      "seatClassName": "ECONOMY",
      "window":true,
      "aisle": false,
      "extraLegroom": true,
      "exitRow": true
    },
    {
      "seatNumber": "11C",
      "rowNumber": 11,
      "seatLetter": "C",
      "seatClassName": "ECONOMY",
      "window": false,
      "aisle": true,
      "extraLegroom": true,
      "exitRow": true
    },
    {
      "seatNumber": "11D",
      "rowNumber": 11,
      "seatLetter": "D",
      "seatClassName": "ECONOMY",
      "window": false,
      "aisle": true,
      "extraLegroom": true,
      "exitRow": true
    },
    {
      "seatNumber": "11F",
      "rowNumber": 11,
      "seatLetter": "F",
      "seatClassName": "ECONOMY",
      "window": true,
      "aisle": false,
      "extraLegroom": true,
      "exitRow": true
    },
    {
      "seatNumber": "12A",
      "rowNumber": 12,
      "seatLetter": "A",
      "seatClassName": "ECONOMY",
      "window":true,
      "aisle": false,
      "extraLegroom": false,
      "exitRow": true
    },
    {
      "seatNumber": "12C",
      "rowNumber": 12,
      "seatLetter": "C",
      "seatClassName": "ECONOMY",
      "window": false,
      "aisle": true,
      "extraLegroom": false,
      "exitRow": true
    },
    {
      "seatNumber": "12D",
      "rowNumber": 12,
      "seatLetter": "D",
      "seatClassName": "ECONOMY",
      "window": false,
      "aisle": true,
      "extraLegroom": false,
      "exitRow": true
    },
    {
      "seatNumber": "12F",
      "rowNumber": 12,
      "seatLetter": "F",
      "seatClassName": "ECONOMY",
      "window": true,
      "aisle": false,
      "extraLegroom": false,
      "exitRow": true
    },
    {
      "seatNumber": "13A",
      "rowNumber": 13,
      "seatLetter": "A",
      "seatClassName": "ECONOMY",
      "window":true,
      "aisle": false,
      "extraLegroom": false,
      "exitRow": false
    },
    {
      "seatNumber": "13C",
      "rowNumber": 13,
      "seatLetter": "C",
      "seatClassName": "ECONOMY",
      "window": false,
      "aisle": true,
      "extraLegroom": false,
      "exitRow": false
    },
    {
      "seatNumber": "13D",
      "rowNumber": 13,
      "seatLetter": "D",
      "seatClassName": "ECONOMY",
      "window": false,
      "aisle": true,
      "extraLegroom": false,
      "exitRow": false
    },
    {
      "seatNumber": "13F",
      "rowNumber": 13,
      "seatLetter": "F",
      "seatClassName": "ECONOMY",
      "window": true,
      "aisle": false,
      "extraLegroom": false,
      "exitRow": false
    },
    {
      "seatNumber": "14A",
      "rowNumber": 14,
      "seatLetter": "A",
      "seatClassName": "ECONOMY",
      "window":true,
      "aisle": false,
      "extraLegroom": false,
      "exitRow": false
    },
    {
      "seatNumber": "14C",
      "rowNumber": 14,
      "seatLetter": "C",
      "seatClassName": "ECONOMY",
      "window": false,
      "aisle": true,
      "extraLegroom": false,
      "exitRow": false
    },
    {
      "seatNumber": "14D",
      "rowNumber": 14,
      "seatLetter": "D",
      "seatClassName": "ECONOMY",
      "window": false,
      "aisle": true,
      "extraLegroom": false,
      "exitRow": false
    },
    {
      "seatNumber": "14F",
      "rowNumber": 14,
      "seatLetter": "F",
      "seatClassName": "ECONOMY",
      "window": true,
      "aisle": false,
      "extraLegroom": false,
      "exitRow": false
    },
    {
      "seatNumber": "15A",
      "rowNumber": 15,
      "seatLetter": "A",
      "seatClassName": "ECONOMY",
      "window":true,
      "aisle": false,
      "extraLegroom": false,
      "exitRow": false
    },
    {
      "seatNumber": "15C",
      "rowNumber": 15,
      "seatLetter": "C",
      "seatClassName": "ECONOMY",
      "window": false,
      "aisle": true,
      "extraLegroom": false,
      "exitRow": false
    },
    {
      "seatNumber": "15D",
      "rowNumber": 15,
      "seatLetter": "D",
      "seatClassName": "ECONOMY",
      "window": false,
      "aisle": true,
      "extraLegroom": false,
      "exitRow": false
    },
    {
      "seatNumber": "15F",
      "rowNumber": 15,
      "seatLetter": "F",
      "seatClassName": "ECONOMY",
      "window": true,
      "aisle": false,
      "extraLegroom": false,
      "exitRow": false
    },
    {
      "seatNumber": "16A",
      "rowNumber": 16,
      "seatLetter": "A",
      "seatClassName": "ECONOMY",
      "window":true,
      "aisle": false,
      "extraLegroom": false,
      "exitRow": false
    },
    {
      "seatNumber": "16C",
      "rowNumber": 16,
      "seatLetter": "C",
      "seatClassName": "ECONOMY",
      "window": false,
      "aisle": true,
      "extraLegroom": false,
      "exitRow": false
    },
    {
      "seatNumber": "16D",
      "rowNumber": 16,
      "seatLetter": "D",
      "seatClassName": "ECONOMY",
      "window": false,
      "aisle": true,
      "extraLegroom": false,
      "exitRow": false
    },
    {
      "seatNumber": "16F",
      "rowNumber": 16,
      "seatLetter": "F",
      "seatClassName": "ECONOMY",
      "window": true,
      "aisle": false,
      "extraLegroom": false,
      "exitRow": false
    },
    {
      "seatNumber": "17A",
      "rowNumber": 17,
      "seatLetter": "A",
      "seatClassName": "ECONOMY",
      "window":true,
      "aisle": false,
      "extraLegroom": false,
      "exitRow": false
    },
    {
      "seatNumber": "17C",
      "rowNumber": 17,
      "seatLetter": "C",
      "seatClassName": "ECONOMY",
      "window": false,
      "aisle": true,
      "extraLegroom": false,
      "exitRow": false
    },
    {
      "seatNumber": "17D",
      "rowNumber": 17,
      "seatLetter": "D",
      "seatClassName": "ECONOMY",
      "window": false,
      "aisle": true,
      "extraLegroom": false,
      "exitRow": false
    },
    {
      "seatNumber": "17F",
      "rowNumber": 17,
      "seatLetter": "F",
      "seatClassName": "ECONOMY",
      "window": true,
      "aisle": false,
      "extraLegroom": false,
      "exitRow": false
    },
    {
      "seatNumber": "18A",
      "rowNumber": 18,
      "seatLetter": "A",
      "seatClassName": "ECONOMY",
      "window":true,
      "aisle": false,
      "extraLegroom": false,
      "exitRow": false
    },
    {
      "seatNumber": "18C",
      "rowNumber": 18,
      "seatLetter": "C",
      "seatClassName": "ECONOMY",
      "window": false,
      "aisle": true,
      "extraLegroom": false,
      "exitRow": false
    },
    {
      "seatNumber": "18D",
      "rowNumber": 18,
      "seatLetter": "D",
      "seatClassName": "ECONOMY",
      "window": false,
      "aisle": true,
      "extraLegroom": false,
      "exitRow": false
    },
    {
      "seatNumber": "18F",
      "rowNumber": 18,
      "seatLetter": "F",
      "seatClassName": "ECONOMY",
      "window": true,
      "aisle": false,
      "extraLegroom": false,
      "exitRow": false
    },
    {
      "seatNumber": "19A",
      "rowNumber": 19,
      "seatLetter": "A",
      "seatClassName": "ECONOMY",
      "window":true,
      "aisle": false,
      "extraLegroom": false,
      "exitRow": false
    },
    {
      "seatNumber": "19C",
      "rowNumber": 19,
      "seatLetter": "C",
      "seatClassName": "ECONOMY",
      "window": false,
      "aisle": true,
      "extraLegroom": false,
      "exitRow": false
    },
    {
      "seatNumber": "19D",
      "rowNumber": 19,
      "seatLetter": "D",
      "seatClassName": "ECONOMY",
      "window": false,
      "aisle": true,
      "extraLegroom": false,
      "exitRow": false
    },
    {
      "seatNumber": "19F",
      "rowNumber": 19,
      "seatLetter": "F",
      "seatClassName": "ECONOMY",
      "window": true,
      "aisle": false,
      "extraLegroom": false,
      "exitRow": false
    },
    {
      "seatNumber": "20A",
      "rowNumber": 20,
      "seatLetter": "A",
      "seatClassName": "ECONOMY",
      "window":true,
      "aisle": false,
      "extraLegroom": false,
      "exitRow": false
    },
    {
      "seatNumber": "20C",
      "rowNumber": 20,
      "seatLetter": "C",
      "seatClassName": "ECONOMY",
      "window": false,
      "aisle": true,
      "extraLegroom": false,
      "exitRow": false
    },
    {
      "seatNumber": "20D",
      "rowNumber": 20,
      "seatLetter": "D",
      "seatClassName": "ECONOMY",
      "window": false,
      "aisle": true,
      "extraLegroom": false,
      "exitRow": false
    },
    {
      "seatNumber": "20F",
      "rowNumber": 20,
      "seatLetter": "F",
      "seatClassName": "ECONOMY",
      "window": true,
      "aisle": false,
      "extraLegroom": false,
      "exitRow": false
    },
    {
      "seatNumber": "21A",
      "rowNumber": 21,
      "seatLetter": "A",
      "seatClassName": "ECONOMY",
      "window":true,
      "aisle": false,
      "extraLegroom": false,
      "exitRow": false
    },
    {
      "seatNumber": "21C",
      "rowNumber": 21,
      "seatLetter": "C",
      "seatClassName": "ECONOMY",
      "window": false,
      "aisle": true,
      "extraLegroom": false,
      "exitRow": false
    },
    {
      "seatNumber": "21D",
      "rowNumber": 21,
      "seatLetter": "D",
      "seatClassName": "ECONOMY",
      "window": false,
      "aisle": true,
      "extraLegroom": false,
      "exitRow": false
    },
    {
      "seatNumber": "21F",
      "rowNumber": 21,
      "seatLetter": "F",
      "seatClassName": "ECONOMY",
      "window": true,
      "aisle": false,
      "extraLegroom": false,
      "exitRow": false
    },
    {
      "seatNumber": "22A",
      "rowNumber": 22,
      "seatLetter": "A",
      "seatClassName": "ECONOMY",
      "window":true,
      "aisle": false,
      "extraLegroom": false,
      "exitRow": false
    },
    {
      "seatNumber": "22C",
      "rowNumber": 22,
      "seatLetter": "C",
      "seatClassName": "ECONOMY",
      "window": false,
      "aisle": true,
      "extraLegroom": false,
      "exitRow": false
    },
    {
      "seatNumber": "22D",
      "rowNumber": 22,
      "seatLetter": "D",
      "seatClassName": "ECONOMY",
      "window": false,
      "aisle": true,
      "extraLegroom": false,
      "exitRow": false
    },
    {
      "seatNumber": "22F",
      "rowNumber": 22,
      "seatLetter": "F",
      "seatClassName": "ECONOMY",
      "window": true,
      "aisle": false,
      "extraLegroom": false,
      "exitRow": false
    },
    {
      "seatNumber": "23A",
      "rowNumber": 23,
      "seatLetter": "A",
      "seatClassName": "ECONOMY",
      "window":true,
      "aisle": false,
      "extraLegroom": false,
      "exitRow": false
    },
    {
      "seatNumber": "23C",
      "rowNumber": 23,
      "seatLetter": "C",
      "seatClassName": "ECONOMY",
      "window": false,
      "aisle": true,
      "extraLegroom": false,
      "exitRow": false
    },
    {
      "seatNumber": "23D",
      "rowNumber": 23,
      "seatLetter": "D",
      "seatClassName": "ECONOMY",
      "window": false,
      "aisle": true,
      "extraLegroom": false,
      "exitRow": false
    },
    {
      "seatNumber": "23F",
      "rowNumber": 23,
      "seatLetter": "F",
      "seatClassName": "ECONOMY",
      "window": true,
      "aisle": false,
      "extraLegroom": false,
      "exitRow": false
    },
    {
      "seatNumber": "24A",
      "rowNumber": 24,
      "seatLetter": "A",
      "seatClassName": "ECONOMY",
      "window":true,
      "aisle": false,
      "extraLegroom": false,
      "exitRow": true
    },
    {
      "seatNumber": "24C",
      "rowNumber": 24,
      "seatLetter": "C",
      "seatClassName": "ECONOMY",
      "window": false,
      "aisle": true,
      "extraLegroom": false,
      "exitRow": true
    },
    {
      "seatNumber": "24D",
      "rowNumber": 24,
      "seatLetter": "D",
      "seatClassName": "ECONOMY",
      "window": false,
      "aisle": true,
      "extraLegroom": false,
      "exitRow": true
    },
    {
      "seatNumber": "24F",
      "rowNumber": 24,
      "seatLetter": "F",
      "seatClassName": "ECONOMY",
      "window": true,
      "aisle": false,
      "extraLegroom": false,
      "exitRow": true
    },
    {
      "seatNumber": "25A",
      "rowNumber": 25,
      "seatLetter": "A",
      "seatClassName": "ECONOMY",
      "window":true,
      "aisle": false,
      "extraLegroom": false,
      "exitRow": true
    },
    {
      "seatNumber": "25C",
      "rowNumber": 25,
      "seatLetter": "C",
      "seatClassName": "ECONOMY",
      "window": false,
      "aisle": true,
      "extraLegroom": false,
      "exitRow": true
    },
    {
      "seatNumber": "25D",
      "rowNumber": 25,
      "seatLetter": "D",
      "seatClassName": "ECONOMY",
      "window": false,
      "aisle": true,
      "extraLegroom": false,
      "exitRow": true
    },
    {
      "seatNumber": "25F",
      "rowNumber": 25,
      "seatLetter": "F",
      "seatClassName": "ECONOMY",
      "window": true,
      "aisle": false,
      "extraLegroom": false,
      "exitRow": true
    }
  ]
}